Metadata-Version: 2.1
Name: shrtfly
Version: 0.0.0.0.3
Summary: Wrappper for https://shrtfly.com/api
Author: Marcuth
Author-email: marcuth2006@gmail.com
License: MIT License
Keywords: ShrtFly wrapper api
License-File: LICENCE
